tests/__init__.py
tests/test_operation_key.py
tests/test_two_xpath_addition.py
tests/test_xpath.py
xpath_string/__init__.py
xpath_string/_operation_key.py
xpath_string/two_xpath_addition.py
xpath_string/xpath.py
xpath_string-0.2.4.dist-info/LICENSE
xpath_string-0.2.4.dist-info/METADATA
xpath_string-0.2.4.dist-info/WHEEL
xpath_string-0.2.4.dist-info/top_level.txt
xpath_string-0.2.4.dist-info/RECORD
